xmoai/__init__.py
xmoai/problems/__init__.py
xmoai/problems/objectives.py
xmoai/problems/restrictions.py
xmoai/problems/xMOAIProblem.py
xmoai/problems/xMOAIRepair.py
xmoai/setup/__init__.py
xmoai/setup/configure.py
xmoai-0.0.dev4.dist-info/LICENSE
xmoai-0.0.dev4.dist-info/METADATA
xmoai-0.0.dev4.dist-info/WHEEL
xmoai-0.0.dev4.dist-info/top_level.txt
xmoai-0.0.dev4.dist-info/RECORD
