Metadata-Version: 2.1
Name: xmoai
Version: 0.0.dev4
Summary: eXplainable Artificial Intelligence using Multiobjective Optimization
Home-page: https://github.com/wmonteiro92/xmoai
Author: Wellington R Monteiro
Author-email: wellington.r.monteiro@gmail.com
License: UNKNOWN
Platform: UNKNOWN
Classifier: Programming Language :: Python :: 3
Classifier: License :: OSI Approved :: MIT License
Classifier: Operating System :: OS Independent
Requires-Python: >=3.6
Requires-Dist: pymoo (>=0.3.0)
Requires-Dist: numpy (>=1.16.0)
Requires-Dist: gower (>=0.0.5)
Requires-Dist: topsis-jamesfallon (>=0.2.3)
